jetraw_tools/__init__.py
jetraw_tools/compression_tool.py
jetraw_tools/config.py
jetraw_tools/core.py
jetraw_tools/dpcore.py
jetraw_tools/image_reader.py
jetraw_tools/jetraw_tiff.py
jetraw_tools/libs.py
jetraw_tools/logger.py
jetraw_tools/main.py
jetraw_tools/parser.py
jetraw_tools/tiff_reader.py
jetraw_tools/tiff_writer.py
jetraw_tools/utils.py
jetraw_tools-0.8.0.dist-info/licenses/LICENCE
jetraw_tools-0.8.0.dist-info/METADATA
jetraw_tools-0.8.0.dist-info/WHEEL
jetraw_tools-0.8.0.dist-info/entry_points.txt
jetraw_tools-0.8.0.dist-info/top_level.txt
jetraw_tools-0.8.0.dist-info/RECORD
