Metadata-Version: 2.4
Name: jetraw-tools
Version: 0.8.0
Summary: A collection of tools and helpers to work with the JetRaw compression libraries.
Author-email: Santiago Cano-Muniz <santiago.cano-muniz@unibas.ch>
Project-URL: Homepage, https://github.com/phisanti/jetraw_tools
Project-URL: Repository, https://github.com/yourusername/jetraw-tools
Classifier: Development Status :: 3 - Alpha
Classifier: Intended Audience :: Developers
Classifier: License :: OSI Approved :: MIT License
Classifier: Programming Language :: Python :: 3
Classifier: Programming Language :: Python :: 3.11
Requires-Python: >=3.8
License-File: LICENCE
Requires-Dist: nd2
Requires-Dist: numpy
Requires-Dist: typer
Requires-Dist: tifffile
Requires-Dist: ome_types
Requires-Dist: rich
Dynamic: license-file
